<?xml version="1.0" encoding="UTF-8" standalone="yes"?>
<database>
    <usuarios>
        <usuario>
            <isFirstAccess>true</isFirstAccess>
            <passagem>
                <gastoMes>2.7300000190734863</gastoMes>
                <gastoTotal>0.0</gastoTotal>
                <saldo>31.269999980926514</saldo>
                <tipoPassagem>UNIVERSITARIO</tipoPassagem>
            </passagem>
            <pathAvatarImagem>/panda.png</pathAvatarImagem>
            <userName>Renan</userName>
        </usuario>
        <usuario>
            <isFirstAccess>true</isFirstAccess>
            <passagem>
                <gastoMes>32.69999885559082</gastoMes>
                <gastoTotal>0.0</gastoTotal>
                <saldo>12.30000114440918</saldo>
                <tipoPassagem>COMUM</tipoPassagem>
            </passagem>
            <pathAvatarImagem>/dog.png</pathAvatarImagem>
            <userName>Mãe</userName>
        </usuario>
    </usuarios>
</database>
